pyamber/__init__.py
pyamber/enum.py
pyamber/features.py
pyamber/flask_amberdata.py
pyamber/intervals.py
pyamber/markets.py
pyamber/request.py
pyamber/util.py
pyamber-0.5.21.dist-info/METADATA
pyamber-0.5.21.dist-info/WHEEL
pyamber-0.5.21.dist-info/licenses/LICENSE
pyamber-0.5.21.dist-info/RECORD
