Metadata-Version: 2.4
Name: pyamber
Version: 0.5.21
Summary: Interact with Amber
Project-URL: repository, https://github.com/tschm/amberdata
Project-URL: issues, https://github.com/tschm/amberdata/issues
Author-email: Thomas Schmelzer <thomas.schmelzer@gmail.com>
License-Expression: MIT
License-File: LICENSE
Classifier: Operating System :: OS Independent
Classifier: Programming Language :: Python :: 3
Requires-Python: >=3.10
Requires-Dist: flask>=3.1.0
Requires-Dist: pandas>=2.2.3
Requires-Dist: requests>=2.32.3
